brdocvalidator/__init__.py
brdocvalidator/brdocvalidator.py
brdocvalidator/tests.py
brdocvalidator-0.0.9.dist-info/METADATA
brdocvalidator-0.0.9.dist-info/WHEEL
brdocvalidator-0.0.9.dist-info/top_level.txt
brdocvalidator-0.0.9.dist-info/RECORD
