Metadata-Version: 2.1
Name: brdocvalidator
Version: 0.0.9
Summary: Library to validate brazilians documents, email, birthDate and others
Home-page: UNKNOWN
Author: rafaelscone (Rafael Schneider)
Author-email: <pipbrvalidator@impaire.com>
License: UNKNOWN
Keywords: python,validation,cpf,cnpj
Platform: UNKNOWN
Classifier: Development Status :: 1 - Planning
Classifier: Intended Audience :: Developers
Classifier: Programming Language :: Python :: 3
Classifier: Operating System :: Unix
Classifier: Operating System :: MacOS :: MacOS X
Classifier: Operating System :: Microsoft :: Windows
Requires-Dist: PyJWT (==2.6.0)
Requires-Dist: bcrypt (==4.0.1)
